[
  {
    "kanji": "悪",
    "yomi": "アク、オ、わるい",
    "meaning": "わるい",
    "examples": [
      "具合（ぐあい）が悪い",
      "悪夢（む）を見る"
    ],
    "readings": {
      "具合（ぐあい）が悪い": "具合（ぐあい）がワルい",
      "悪夢（む）を見る": "アク夢（む）を見る"
    }
  },
  {
    "kanji": "安",
    "yomi": "アン、やすい",
    "meaning": "やすい",
    "examples": [
      "安い品物（しなもの）",
      "安全がだいじ"
    ],
    "readings": {
      "安い品物（しなもの）": "ヤスい品物（しなもの）",
      "安全がだいじ": "アン全がだいじ"
    }
  },
  {
    "kanji": "暗",
    "yomi": "アン、くらい",
    "meaning": "くらい",
    "examples": [
      "暗い部屋（へや）",
      "暗算をする"
    ],
    "readings": {
      "暗算をする": "アン算をする",
      "暗い部屋（へや）": "クラい部屋（へや）"
    }
  },
  {
    "kanji": "医",
    "yomi": "イ",
    "meaning": "いしゃ",
    "examples": [
      "医者になる",
      "医学を学ぶ"
    ],
    "readings": {
      "医学を学ぶ": "イ学を学ぶ",
      "医者になる": "イ者になる"
    }
  },
  {
    "kanji": "委",
    "yomi": "イ、ゆだねる",
    "meaning": "ゆだねる",
    "examples": [
      "委員（いん）になる",
      "身（み）を委ねる"
    ],
    "readings": {
      "委員（いん）になる": "イ員（いん）になる",
      "身（み）を委ねる": "身（み）をユダねる"
    }
  },
  {
    "kanji": "意",
    "yomi": "イ",
    "meaning": "こころ",
    "examples": [
      "意味（み）を知る",
      "意見を言う"
    ],
    "readings": {
      "意見を言う": "イ見を言う",
      "意味（み）を知る": "イ味（み）を知る"
    }
  },
  {
    "kanji": "育",
    "yomi": "イク、そだつ、そだてる",
    "meaning": "そだてる",
    "examples": [
      "花を育てる",
      "体育館（かん）に行く"
    ],
    "readings": {
      "花を育てる": "花をソダてる",
      "体育館（かん）に行く": "体イク館に行く"
    }
  },
  {
    "kanji": "員",
    "yomi": "イン",
    "meaning": "ひと",
    "examples": [
      "会社員",
      "全員集合（しゅうごう）"
    ],
    "readings": {
      "会社員": "会社インになる",
      "全員集合（しゅうごう）": "全イン集合（しゅうごう）"
    }
  },
  {
    "kanji": "院",
    "yomi": "イン",
    "meaning": "やかた",
    "examples": [
      "病（びょう）院に行く",
      "大学院にすすむ"
    ],
    "readings": {
      "病（びょう）院に行く": "病（びょう）インに行く",
      "大学院にすすむ": "大学インにすすむ"
    }
  },
  {
    "kanji": "飲",
    "yomi": "イン、のむ",
    "meaning": "のむ",
    "examples": [
      "水を飲む",
      "町の飲食店"
    ],
    "readings": {
      "水を飲む": "水をノム",
      "町の飲食店": "町のイン食店"
    }
  },
  {
    "kanji": "運",
    "yomi": "ウン、はこぶ",
    "meaning": "はこぶ",
    "examples": [
      "荷物（にもつ）を運ぶ",
      "運動会"
    ],
    "readings": {
      "運動会": "ウン動会",
      "荷物（にもつ）を運ぶ": "荷物（にもつ）をハコぶ"
    }
  },
  {
    "kanji": "泳",
    "yomi": "エイ、およぐ",
    "meaning": "およぐ",
    "examples": [
      "海で泳ぐ",
      "水泳大会"
    ],
    "readings": {
      "海で泳ぐ": "海でオヨぐ",
      "水泳大会": "水エイ大会"
    }
  },
  {
    "kanji": "駅",
    "yomi": "エキ",
    "meaning": "えき",
    "examples": [
      "駅前でまつ",
      "東京駅から出発する"
    ],
    "readings": {
      "駅前でまつ": "エキ前でまつ",
      "東京駅から出発する": "東京エキから出発する"
    }
  },
  {
    "kanji": "央",
    "yomi": "オウ",
    "meaning": "なかば",
    "examples": [
      "中央線（せん）をはみだす",
      "町の中央"
    ],
    "readings": {
      "町の中央": "町の中オウ",
      "中央線（せん）をはみだす": "中オウ線（せん）をはみだす"
    }
  },
  {
    "kanji": "横",
    "yomi": "オウ、よこ",
    "meaning": "よこ",
    "examples": [
      "横をむく",
      "横断（だん）歩道"
    ],
    "readings": {
      "横をむく": "ヨコをむく",
      "横断（だん）歩道": "オウ断（だん）歩道"
    }
  },
  {
    "kanji": "屋",
    "yomi": "オク、や",
    "meaning": "や",
    "examples": [
      "八百屋で買う",
      "屋上に上がる"
    ],
    "readings": {
      "八百屋で買う": "八百ヤで買う",
      "屋上に上がる": "オク上に上がる"
    }
  },
  {
    "kanji": "温",
    "yomi": "オン、あたたか、あたたかい",
    "meaning": "あたたかい",
    "examples": [
      "温かいお茶",
      "温度計ではかる"
    ],
    "readings": {
      "温かいお茶": "アタタカいお茶",
      "温度計ではかる": "オン度計ではかる"
    }
  },
  {
    "kanji": "化",
    "yomi": "カ、ケ、ばける、ばかす",
    "meaning": "ばける",
    "examples": [
      "お化けが出た",
      "化学を学ぶ"
    ],
    "readings": {
      "お化けが出た": "おバけが出た",
      "化学を学ぶ": "カ学を学ぶ"
    }
  },
  {
    "kanji": "荷",
    "yomi": "カ、に",
    "meaning": "に",
    "examples": [
      "おもい荷物",
      "荷台にのせる"
    ],
    "readings": {
      "おもい荷物": "おもいニ物",
      "荷台にのせる": "ニ台にのせる"
    }
  },
  {
    "kanji": "界",
    "yomi": "カイ",
    "meaning": "さかい",
    "examples": [
      "世界一周りょこうに行く",
      "視（し）界が悪い"
    ],
    "readings": {
      "世界一周りょこうに行く": "世カイ一周りょこうに行く",
      "視（し）界が悪い": "視（し）カイが悪い"
    }
  },
  {
    "kanji": "開",
    "yomi": "カイ、ひらく、ひらける、あく、あける",
    "meaning": "ひらく",
    "examples": [
      "ドアを開ける",
      "開始する"
    ],
    "readings": {
      "ドアを開ける": "ドアをアける",
      "開始する": "カイ始する"
    }
  },
  {
    "kanji": "階",
    "yomi": "カイ、きざはし",
    "meaning": "きざはし",
    "examples": [
      "二階に上がる",
      "階段をのぼる"
    ],
    "readings": {
      "二階に上がる": "二カイに上がる",
      "階段をのぼる": "カイ段をのぼる"
    }
  },
  {
    "kanji": "寒",
    "yomi": "カン、さむい",
    "meaning": "さむい",
    "examples": [
      "寒い冬",
      "悪（お）寒がする"
    ],
    "readings": {
      "寒い冬": "サムい冬",
      "悪（お）寒がする": "悪（お）カンがする"
    }
  },
  {
    "kanji": "感",
    "yomi": "カン",
    "meaning": "かんじる",
    "examples": [
      "感動する",
      "感想文を書く"
    ],
    "readings": {
      "感動する": "カン動する",
      "感想文を書く": "カン想文を書く"
    }
  },
  {
    "kanji": "漢",
    "yomi": "カン",
    "meaning": "から",
    "examples": [
      "漢字を書く",
      "漢和辞典（じてん）"
    ],
    "readings": {
      "漢字を書く": "カン字を書く",
      "漢和辞典（じてん）": "カン和辞典（じてん）"
    }
  },
  {
    "kanji": "館",
    "yomi": "カン、やかた",
    "meaning": "やかた",
    "examples": [
      "図書館に行く",
      "映画（えいが）館に行く"
    ],
    "readings": {
      "図書館に行く": "図書カンに行く",
      "映画（えいが）館に行く": "映画（えいが）カンに行く"
    }
  },
  {
    "kanji": "岸",
    "yomi": "ガン、きし",
    "meaning": "きし",
    "examples": [
      "川岸を歩く",
      "海岸ぞいを歩く"
    ],
    "readings": {
      "川岸を歩く": "川ギシを歩く",
      "海岸ぞいを歩く": "海ガンぞいを歩く"
    }
  },
  {
    "kanji": "起",
    "yomi": "キ、おきる、おこる、おこす",
    "meaning": "おきる",
    "examples": [
      "朝早く起きる",
      "起立する"
    ],
    "readings": {
      "朝早く起きる": "朝早くオきる",
      "起立する": "キ立する"
    }
  },
  {
    "kanji": "期",
    "yomi": "キ、ゴ",
    "meaning": "とき",
    "examples": [
      "一学期がおわる",
      "期待（たい）する"
    ],
    "readings": {
      "一学期がおわる": "一学キがおわる",
      "期待（たい）する": "キ待（たい）する"
    }
  },
  {
    "kanji": "客",
    "yomi": "キャク、カク",
    "meaning": "きゃく",
    "examples": [
      "お客さん",
      "たくさんの乗（じょう）客"
    ],
    "readings": {
      "お客さん": "おキャクさん",
      "たくさんの乗（じょう）客": "たくさんの乗（じょう）キャク"
    }
  },
  {
    "kanji": "究",
    "yomi": "キュウ、きわめる",
    "meaning": "きわめる",
    "examples": [
      "研（けん）究する",
      "学びを究める"
    ],
    "readings": {
      "研（けん）究する": "研（けん）キュウする",
      "学びを究める": "学びをキワめる"
    }
  },
  {
    "kanji": "急",
    "yomi": "キュウ、いそぐ",
    "meaning": "いそぐ",
    "examples": [
      "急いで行く",
      "急行電車にのる"
    ],
    "readings": {
      "急いで行く": "イソいで行く",
      "急行電車にのる": "キュウ行電車にのる"
    }
  },
  {
    "kanji": "級",
    "yomi": "キュウ",
    "meaning": "しな",
    "examples": [
      "学級会をひらく",
      "上級生になる"
    ],
    "readings": {
      "学級会をひらく": "学キュウ会をひらく",
      "上級生になる": "上キュウ生になる"
    }
  },
  {
    "kanji": "宮",
    "yomi": "キュウ、グウ、ク、みや",
    "meaning": "みや",
    "examples": [
      "お宮参（まい）り",
      "王宮への道"
    ],
    "readings": {
      "お宮参（まい）り": "おミヤ参（まい）り",
      "王宮への道": "王キュウへの道"
    }
  },
  {
    "kanji": "球",
    "yomi": "キュウ、たま",
    "meaning": "たま",
    "examples": [
      "野球をする",
      "電球をかえる"
    ],
    "readings": {
      "野球をする": "野キュウをする",
      "電球をかえる": "電キュウをかえる"
    }
  },
  {
    "kanji": "去",
    "yomi": "キョ、コ、さる",
    "meaning": "さる",
    "examples": [
      "冬が去る",
      "去年の夏"
    ],
    "readings": {
      "冬が去る": "冬がサる",
      "去年の夏": "キョ年の夏"
    }
  },
  {
    "kanji": "橋",
    "yomi": "キョウ、はし",
    "meaning": "はし",
    "examples": [
      "橋をわたる",
      "歩道橋をわたる"
    ],
    "readings": {
      "橋をわたる": "ハシをわたる",
      "歩道橋をわたる": "歩道キョウをわたる"
    }
  },
  {
    "kanji": "業",
    "yomi": "ギョウ、ゴウ、わざ",
    "meaning": "わざ",
    "examples": [
      "授業を受ける",
      "すさまじい早業"
    ],
    "readings": {
      "授業を受ける": "授ギョウを受ける",
      "すさまじい早業": "すさまじい早ワザ"
    }
  },
  {
    "kanji": "曲",
    "yomi": "キョク、まがる、まげる",
    "meaning": "まがる",
    "examples": [
      "角を曲がる",
      "名曲をきく"
    ],
    "readings": {
      "角を曲がる": "角をマがる",
      "名曲をきく": "名キョクをきく"
    }
  },
  {
    "kanji": "局",
    "yomi": "キョク",
    "meaning": "つぼね",
    "examples": [
      "郵便（ゆうびん）局",
      "テレビの放送（ほうそう）局"
    ],
    "readings": {
      "郵便（ゆうびん）局": "郵便（ゆうびん）キョク",
      "テレビの放送（ほうそう）局": "テレビの放送（ほうそう）キョク"
    }
  },
  {
    "kanji": "銀",
    "yomi": "ギン、しろがね",
    "meaning": "しろがね",
    "examples": [
      "銀行にお金をあずける",
      "銀色の車"
    ],
    "readings": {
      "銀色の車": "ギン色の車",
      "銀行にお金をあずける": "ギン行にお金をあずける"
    }
  },
  {
    "kanji": "区",
    "yomi": "ク",
    "meaning": "わける",
    "examples": [
      "区切る",
      "地区センター"
    ],
    "readings": {
      "区切る": "ク切る",
      "地区センター": "地クセンター"
    }
  },
  {
    "kanji": "苦",
    "yomi": "ク、くるしい、くるしむ、くるしめる、にがい、にがる",
    "meaning": "くるしい",
    "examples": [
      "いきが苦しい",
      "苦労（ろう）する"
    ],
    "readings": {
      "いきが苦しい": "いきがクルしい",
      "苦労（ろう）する": "ク労（ろう）する"
    }
  },
  {
    "kanji": "具",
    "yomi": "グ、そなえる",
    "meaning": "そなえる",
    "examples": [
      "道具をつかう",
      "家具を買う"
    ],
    "readings": {
      "道具をつかう": "道グをつかう",
      "家具を買う": "家グを買う"
    }
  },
  {
    "kanji": "君",
    "yomi": "クン、きみ",
    "meaning": "きみ",
    "examples": [
      "君の名は",
      "すばらしい君主"
    ],
    "readings": {
      "君の名は": "キミの名は",
      "すばらしい君主": "すばらしいクン主"
    }
  },
  {
    "kanji": "係",
    "yomi": "ケイ、かかり、かかる",
    "meaning": "かかる",
    "examples": [
      "係を決める",
      "関係がある"
    ],
    "readings": {
      "係を決める": "カカリを決める",
      "関係がある": "関ケイがある"
    }
  },
  {
    "kanji": "軽",
    "yomi": "ケイ、かるい、かろやか",
    "meaning": "かるい",
    "examples": [
      "軽い荷物（にもつ）",
      "軽食をとる"
    ],
    "readings": {
      "軽食をとる": "ケイ食をとる",
      "軽い荷物（にもつ）": "カルい荷物（にもつ）"
    }
  },
  {
    "kanji": "血",
    "yomi": "ケツ、ち",
    "meaning": "ち",
    "examples": [
      "血が出る",
      "出血する"
    ],
    "readings": {
      "血が出る": "チが出る",
      "出血する": "出ケツする"
    }
  },
  {
    "kanji": "決",
    "yomi": "ケツ、きめる、きまる",
    "meaning": "きめる",
    "examples": [
      "心を決める",
      "決心する"
    ],
    "readings": {
      "決心する": "ケッ心する",
      "心を決める": "心をキめる"
    }
  },
  {
    "kanji": "研",
    "yomi": "ケン、とぐ",
    "meaning": "とぐ",
    "examples": [
      "包丁（ほうちょう）を研ぐ",
      "研究室にはいる"
    ],
    "readings": {
      "包丁（ほうちょう）を研ぐ": "包丁（ほうちょう）をトぐ",
      "研究室にはいる": "ケン究室にはいる"
    }
  },
  {
    "kanji": "県",
    "yomi": "ケン",
    "meaning": "あがた",
    "examples": [
      "県知事と会う",
      "青森県に行く"
    ],
    "readings": {
      "県知事と会う": "ケン知事と会う",
      "青森県に行く": "青森ケンに行く"
    }
  },
  {
    "kanji": "庫",
    "yomi": "コ、くら",
    "meaning": "くら",
    "examples": [
      "金庫をあける",
      "車庫に車を入れる"
    ],
    "readings": {
      "金庫をあける": "金コをあける",
      "車庫に車を入れる": "車コに車を入れる"
    }
  },
  {
    "kanji": "湖",
    "yomi": "コ、みずうみ",
    "meaning": "みずうみ",
    "examples": [
      "湖であそぶ",
      "びわ湖を見に行く"
    ],
    "readings": {
      "湖であそぶ": "ミズウミであそぶ",
      "びわ湖を見に行く": "びわコを見に行く"
    }
  },
  {
    "kanji": "向",
    "yomi": "コウ、むく、むける、むかう、むこう",
    "meaning": "むく",
    "examples": [
      "向こうがわ",
      "方向おんちな人"
    ],
    "readings": {
      "向こうがわ": "ムこうがわ",
      "方向おんちな人": "方コウおんちな人"
    }
  },
  {
    "kanji": "幸",
    "yomi": "コウ、さいわい、さち、しあわせ",
    "meaning": "しあわせ",
    "examples": [
      "幸せな時",
      "幸福な人生"
    ],
    "readings": {
      "幸せな時": "シアワせな時",
      "幸福な人生": "コウ福な人生"
    }
  },
  {
    "kanji": "港",
    "yomi": "コウ、みなと",
    "meaning": "みなと",
    "examples": [
      "港町がある",
      "空港に行く"
    ],
    "readings": {
      "港町がある": "ミナト町がある",
      "空港に行く": "空コウに行く"
    }
  },
  {
    "kanji": "号",
    "yomi": "ゴウ、さけぶ、よびな",
    "meaning": "よびな",
    "examples": [
      "記号を書く",
      "年号をおぼえる"
    ],
    "readings": {
      "記号を書く": "記ゴウをかく",
      "年号をおぼえる": "年ゴウをおぼえる"
    }
  },
  {
    "kanji": "根",
    "yomi": "コン、ね",
    "meaning": "ね",
    "examples": [
      "木の根",
      "大根をひきぬく"
    ],
    "readings": {
      "木の根": "木のネ",
      "大根をひきぬく": "大コンをひきぬく"
    }
  },
  {
    "kanji": "祭",
    "yomi": "サイ、まつる、まつり",
    "meaning": "まつり",
    "examples": [
      "夏祭りをたのしむ",
      "文化祭の出し物"
    ],
    "readings": {
      "夏祭りをたのしむ": "夏マツりをたのしむ",
      "文化祭の出し物": "文化サイの出し物"
    }
  },
  {
    "kanji": "皿",
    "yomi": "ベイ、さら",
    "meaning": "さら",
    "examples": [
      "お皿をあらう",
      "紙皿をくばる"
    ],
    "readings": {
      "お皿をあらう": "おサラをあらう",
      "紙皿をくばる": "紙ザラをくばる"
    }
  },
  {
    "kanji": "仕",
    "yomi": "シ、ジ、つかえる",
    "meaning": "つかえる",
    "examples": [
      "仕事がいそがしい",
      "主人に仕える"
    ],
    "readings": {
      "仕事がいそがしい": "シ事がいそがしい",
      "主人に仕える": "主人にツカえる"
    }
  },
  {
    "kanji": "死",
    "yomi": "シ、しぬ",
    "meaning": "しぬ",
    "examples": [
      "死ぬ気でたたかう",
      "必死にがんばる"
    ],
    "readings": {
      "死ぬ気でたたかう": "シぬ気でたたかう",
      "必死にがんばる": "必シにがんばる"
    }
  },
  {
    "kanji": "使",
    "yomi": "シ、つかう",
    "meaning": "つかう",
    "examples": [
      "道具を使う",
      "使用する"
    ],
    "readings": {
      "道具を使う": "道具をツカう",
      "使用する": "シ用する"
    }
  },
  {
    "kanji": "始",
    "yomi": "シ、はじめる、はじまる",
    "meaning": "はじめる",
    "examples": [
      "テストを始める",
      "明日は始業式"
    ],
    "readings": {
      "テストを始める": "テストをハジめる",
      "明日は始業式": "明日はシ業式"
    }
  },
  {
    "kanji": "指",
    "yomi": "シ、ゆび、さす",
    "meaning": "ゆび",
    "examples": [
      "指でさす",
      "指定席を買う"
    ],
    "readings": {
      "指でさす": "ユビでさす",
      "指定席を買う": "シ定席を買う"
    }
  },
  {
    "kanji": "歯",
    "yomi": "シ、は",
    "meaning": "は",
    "examples": [
      "歯をみがく",
      "歯医者になる"
    ],
    "readings": {
      "歯をみがく": "ハをみがく",
      "歯医者になる": "ハ医者になる"
    }
  },
  {
    "kanji": "詩",
    "yomi": "シ、うた",
    "meaning": "うた",
    "examples": [
      "詩を書く",
      "有名な詩人"
    ],
    "readings": {
      "詩を書く": "シを書く",
      "有名な詩人": "有名なシ人"
    }
  },
  {
    "kanji": "次",
    "yomi": "ジ、シ、つぐ、つぎ",
    "meaning": "つぎ",
    "examples": [
      "次の日",
      "目次を見る"
    ],
    "readings": {
      "次の日": "ツギの日",
      "目次を見る": "目ジを見る"
    }
  },
  {
    "kanji": "事",
    "yomi": "ジ、ズ、こと、つかう",
    "meaning": "こと",
    "examples": [
      "大事なこと",
      "仕事がいそがしい"
    ],
    "readings": {
      "大事なこと": "大ジなこと",
      "仕事がいそがしい": "仕ゴトがいそがしい"
    }
  },
  {
    "kanji": "持",
    "yomi": "ジ、もつ、もてる",
    "meaning": "もつ",
    "examples": [
      "荷物を持つ",
      "持参する"
    ],
    "readings": {
      "荷物を持つ": "荷物をモつ",
      "持参する": "ジ参する"
    }
  },
  {
    "kanji": "式",
    "yomi": "シキ",
    "meaning": "のり",
    "examples": [
      "明日は入学式",
      "計算式を書く"
    ],
    "readings": {
      "明日は入学式": "明日は入学シキ",
      "計算式を書く": "計算シキを書く"
    }
  },
  {
    "kanji": "実",
    "yomi": "ジツ、み、みのる",
    "meaning": "みのる",
    "examples": [
      "木の実をひろう",
      "事実をかくにんする"
    ],
    "readings": {
      "木の実をひろう": "木のミをひろう",
      "事実をかくにんする": "事ジツをかくにんする"
    }
  },
  {
    "kanji": "写",
    "yomi": "シャ、うつす、うつる",
    "meaning": "うつす",
    "examples": [
      "写真をとる",
      "港で写生する"
    ],
    "readings": {
      "写真をとる": "シャ真をとる",
      "港で写生する": "港でシャ生する"
    }
  },
  {
    "kanji": "者",
    "yomi": "シャ、もの",
    "meaning": "もの",
    "examples": [
      "若者のあつまるまち",
      "医者をめざす"
    ],
    "readings": {
      "若者のあつまるまち": "若モノのあつまるまち",
      "医者をめざす": "医シャをめざす"
    }
  },
  {
    "kanji": "主",
    "yomi": "シュ、ス、ぬし、おも",
    "meaning": "ぬし",
    "examples": [
      "主な理由",
      "主人公にあこがれる"
    ],
    "readings": {
      "主な理由": "オモな理由",
      "主人公にあこがれる": "シュ人公にあこがれる"
    }
  },
  {
    "kanji": "守",
    "yomi": "シュ、ス、まもる、もり",
    "meaning": "まもる",
    "examples": [
      "約束を守る",
      "留守番をする"
    ],
    "readings": {
      "約束を守る": "約束をマモる",
      "留守番をする": "留ス番をする"
    }
  },
  {
    "kanji": "取",
    "yomi": "シュ、とる",
    "meaning": "とる",
    "examples": [
      "草を取る",
      "取材をうける"
    ],
    "readings": {
      "草を取る": "草をトる",
      "取材をうける": "シュ材をうける"
    }
  },
  {
    "kanji": "酒",
    "yomi": "シュ、さけ、さか",
    "meaning": "さけ",
    "examples": [
      "お酒を飲む",
      "酒屋で買う"
    ],
    "readings": {
      "お酒を飲む": "おサケを飲む",
      "酒屋で買う": "サカ屋で買う"
    }
  },
  {
    "kanji": "受",
    "yomi": "ジュ、うける、うかる",
    "meaning": "うける",
    "examples": [
      "テストを受ける",
      "受験する"
    ],
    "readings": {
      "受験する": "ジュ験する",
      "テストを受ける": "テストをウける"
    }
  },
  {
    "kanji": "州",
    "yomi": "シュウ、す",
    "meaning": "す",
    "examples": [
      "九州にすんでいる",
      "州知事"
    ],
    "readings": {
      "州知事": "シュウ知事と話す",
      "九州にすんでいる": "九シュウにすんでいる"
    }
  },
  {
    "kanji": "拾",
    "yomi": "シュウ、ジュウ、ひろう",
    "meaning": "ひろう",
    "examples": [
      "ゴミを拾う",
      "高価な拾得物"
    ],
    "readings": {
      "ゴミを拾う": "ゴミをヒロう",
      "高価な拾得物": "高価なシュウ得物"
    }
  },
  {
    "kanji": "終",
    "yomi": "シュウ、おわる、おえる",
    "meaning": "おわる",
    "examples": [
      "れんしゅうが終わる",
      "電車の終点"
    ],
    "readings": {
      "れんしゅうが終わる": "れんしゅうがオわる",
      "電車の終点": "電車のシュウ点"
    }
  },
  {
    "kanji": "習",
    "yomi": "シュウ、ならう",
    "meaning": "ならう",
    "examples": [
      "ピアノを習う",
      "習字を習う"
    ],
    "readings": {
      "ピアノを習う": "ピアノをナラう",
      "習字を習う": "シュウ字をナラう"
    }
  },
  {
    "kanji": "集",
    "yomi": "シュウ、あつまる、あつめる、つどう",
    "meaning": "あつまる",
    "examples": [
      "校庭に集まる",
      "全員集合する"
    ],
    "readings": {
      "校庭に集まる": "校庭にアツまる",
      "全員集合する": "全員シュウ合する"
    }
  },
  {
    "kanji": "住",
    "yomi": "ジュウ、すむ、すまう",
    "meaning": "すむ",
    "examples": [
      "町に住む",
      "住所を書く"
    ],
    "readings": {
      "町に住む": "町にスむ",
      "住所を書く": "ジュウ所を書く"
    }
  },
  {
    "kanji": "重",
    "yomi": "ジュウ、チョウ、おもい、かさねる、かさなる、え",
    "meaning": "おもい",
    "examples": [
      "重いにもつ",
      "重大なニュース"
    ],
    "readings": {
      "重大なニュース": "ジュウ大なニュース",
      "重いにもつ": "オモいにもつ"
    }
  },
  {
    "kanji": "宿",
    "yomi": "シュク、やど、やどる、やどす",
    "meaning": "やど",
    "examples": [
      "宿にとまる",
      "夏休みの宿題"
    ],
    "readings": {
      "夏休みの宿題": "夏休みのシュク題",
      "宿にとまる": "ヤドにとまる"
    }
  },
  {
    "kanji": "所",
    "yomi": "ショ、ところ",
    "meaning": "ところ",
    "examples": [
      "所により一時雨",
      "住所を教える"
    ],
    "readings": {
      "住所を教える": "住ショを教える",
      "所により一時雨": "トコロにより一時雨"
    }
  },
  {
    "kanji": "暑",
    "yomi": "ショ、あつい",
    "meaning": "あつい",
    "examples": [
      "暑い日がつづく",
      "暑中見舞（ま）い"
    ],
    "readings": {
      "暑い日がつづく": "アツい日がつづく",
      "暑中見舞（ま）い": "ショ中見舞（ま）い"
    }
  },
  {
    "kanji": "助",
    "yomi": "ジョ、たすける、たすかる、すけ",
    "meaning": "たすける",
    "examples": [
      "人を助ける",
      "車の助手席（せき）"
    ],
    "readings": {
      "人を助ける": "人をタスける",
      "車の助手席（せき）": "車のジョ手席（せき）"
    }
  },
  {
    "kanji": "昭",
    "yomi": "ショウ",
    "meaning": "あきらか",
    "examples": [
      "昭和の時代",
      "昭和の日"
    ],
    "readings": {
      "昭和の時代": "ショウ和の時代",
      "昭和の日": "ショウ和の日"
    }
  },
  {
    "kanji": "消",
    "yomi": "ショウ、きえる、けす",
    "meaning": "きえる",
    "examples": [
      "火を消す",
      "消しゴムを使う"
    ],
    "readings": {
      "火を消す": "火をケす",
      "消しゴムを使う": "ケしゴムを使う"
    }
  },
  {
    "kanji": "商",
    "yomi": "ショウ、あきなう",
    "meaning": "あきなう",
    "examples": [
      "商売を始める",
      "商いを始める"
    ],
    "readings": {
      "商売を始める": "ショウ売を始める",
      "商いを始める": "アキナいを始める"
    }
  },
  {
    "kanji": "章",
    "yomi": "ショウ",
    "meaning": "あや",
    "examples": [
      "文章を読む",
      "第一章から読む"
    ],
    "readings": {
      "文章を読む": "文ショウを読む",
      "第一章から読む": "第一ショウから読む"
    }
  },
  {
    "kanji": "勝",
    "yomi": "ショウ、かつ、まさる",
    "meaning": "かつ",
    "examples": [
      "試合に勝つ",
      "決勝戦（せん）に出る"
    ],
    "readings": {
      "試合に勝つ": "試合にカつ",
      "決勝戦（せん）に出る": "決ショウ戦（せん）に出る"
    }
  },
  {
    "kanji": "乗",
    "yomi": "ジョウ、のる、のせる",
    "meaning": "のる",
    "examples": [
      "バスに乗る",
      "乗車券（けん）を買う"
    ],
    "readings": {
      "バスに乗る": "バスにノる",
      "乗車券（けん）を買う": "ジョウ車券（けん）を買う"
    }
  },
  {
    "kanji": "植",
    "yomi": "ショク、うえる、うわる",
    "meaning": "うえる",
    "examples": [
      "花を植える",
      "植物図かん"
    ],
    "readings": {
      "花を植える": "花をウえる",
      "植物図かん": "ショク物図かん"
    }
  },
  {
    "kanji": "申",
    "yomi": "シン、もうす",
    "meaning": "もうす",
    "examples": [
      "名前を申し上げる",
      "申請（せい）をする"
    ],
    "readings": {
      "名前を申し上げる": "名前をモウし上げる",
      "申請（せい）をする": "シン請（せい）をする"
    }
  },
  {
    "kanji": "身",
    "yomi": "シン、み",
    "meaning": "み",
    "examples": [
      "身長をはかる",
      "中身を見る"
    ],
    "readings": {
      "身長をはかる": "シン長をはかる",
      "中身を見る": "中ミを見る"
    }
  },
  {
    "kanji": "神",
    "yomi": "シン、ジン、かみ、かん、こう",
    "meaning": "かみ",
    "examples": [
      "神様（さま）にいのる",
      "神社に行く"
    ],
    "readings": {
      "神社に行く": "ジン社に行く",
      "神様（さま）にいのる": "カミ様（さま）にいのる"
    }
  },
  {
    "kanji": "真",
    "yomi": "シン、ま",
    "meaning": "ま",
    "examples": [
      "真ん中におく",
      "真実を話す"
    ],
    "readings": {
      "真実を話す": "シン実を話す",
      "真ん中におく": "マん中におく"
    }
  },
  {
    "kanji": "深",
    "yomi": "シン、ふかい、ふかまる、ふかめる",
    "meaning": "ふかい",
    "examples": [
      "海が深い",
      "深呼吸（こきゅう）をする"
    ],
    "readings": {
      "海が深い": "海がフカい",
      "深呼吸（こきゅう）をする": "シン呼吸（こきゅう）をする"
    }
  },
  {
    "kanji": "進",
    "yomi": "シン、すすむ、すすめる",
    "meaning": "すすむ",
    "examples": [
      "前に進む",
      "行進をする"
    ],
    "readings": {
      "前に進む": "前にススむ",
      "行進をする": "行シンをする"
    }
  },
  {
    "kanji": "世",
    "yomi": "セイ、セ、よ",
    "meaning": "よ",
    "examples": [
      "世界一周",
      "世の中を知る"
    ],
    "readings": {
      "世界一周": "セ界一周",
      "世の中を知る": "ヨの中を知る"
    }
  },
  {
    "kanji": "整",
    "yomi": "セイ、ととのえる、ととのう",
    "meaning": "ととのえる",
    "examples": [
      "形を整える",
      "整理整頓（とん）する"
    ],
    "readings": {
      "形を整える": "形をトトノえる",
      "整理整頓（とん）する": "セイ理セイ頓（とん）する"
    }
  },
  {
    "kanji": "昔",
    "yomi": "セキ、シャク、むかし",
    "meaning": "むかし",
    "examples": [
      "昔話を聞く",
      "昔のあそび"
    ],
    "readings": {
      "昔話を聞く": "ムカシ話を聞く",
      "昔のあそび": "ムカシのあそび"
    }
  },
  {
    "kanji": "全",
    "yomi": "ゼン、すべて、まったく",
    "meaning": "すべて",
    "examples": [
      "全部食べる",
      "全力を出す"
    ],
    "readings": {
      "全部食べる": "ゼン部食べる",
      "全力を出す": "ゼン力を出す"
    }
  },
  {
    "kanji": "相",
    "yomi": "ソウ、ショウ、あい",
    "meaning": "あい",
    "examples": [
      "相談（だん）にのる",
      "相手を見る"
    ],
    "readings": {
      "相手を見る": "アイ手を見る",
      "相談（だん）にのる": "ソウ（だん）にのる"
    }
  },
  {
    "kanji": "送",
    "yomi": "ソウ、おくる",
    "meaning": "おくる",
    "examples": [
      "手紙を送る",
      "放送を聞く"
    ],
    "readings": {
      "手紙を送る": "手紙をオクる",
      "放送を聞く": "放ソウを聞く"
    }
  },
  {
    "kanji": "想",
    "yomi": "ソウ、ソ、おもう",
    "meaning": "おもう",
    "examples": [
      "予想が当たる",
      "感想を言う"
    ],
    "readings": {
      "予想が当たる": "予ソウが当たる",
      "感想を言う": "感ソウを言う"
    }
  },
  {
    "kanji": "息",
    "yomi": "ソク、いき",
    "meaning": "いき",
    "examples": [
      "息をする",
      "休息をとる"
    ],
    "readings": {
      "息をする": "イキをする",
      "休息をとる": "休ソクをとる"
    }
  },
  {
    "kanji": "速",
    "yomi": "ソク、はやい、はやめる、すみやか",
    "meaning": "はやい",
    "examples": [
      "足が速い",
      "速度をおとす"
    ],
    "readings": {
      "足が速い": "足がハヤい",
      "速度をおとす": "ソク度をおとす"
    }
  },
  {
    "kanji": "族",
    "yomi": "ゾク",
    "meaning": "やから",
    "examples": [
      "家族で出かける",
      "民族いしょう"
    ],
    "readings": {
      "家族で出かける": "家ゾクで出かける",
      "民族いしょう": "民ゾクいしょう"
    }
  },
  {
    "kanji": "他",
    "yomi": "タ、ほか",
    "meaning": "ほか",
    "examples": [
      "他人の家",
      "その他"
    ],
    "readings": {
      "他人の家": "タ人の家",
      "その他": "そのタ"
    }
  },
  {
    "kanji": "打",
    "yomi": "ダ、うつ",
    "meaning": "うつ",
    "examples": [
      "ボールを打つ",
      "一番打者"
    ],
    "readings": {
      "ボールを打つ": "ボールをウつ",
      "一番打者": "一番ダ者"
    }
  },
  {
    "kanji": "対",
    "yomi": "タイ、ツイ、あいて、こたえる",
    "meaning": "あいて",
    "examples": [
      "反対する",
      "ライバルと対決"
    ],
    "readings": {
      "反対する": "ハン対する",
      "ライバルと対決": "ライバルとタイ決"
    }
  },
  {
    "kanji": "待",
    "yomi": "タイ、まつ",
    "meaning": "まつ",
    "examples": [
      "バスを待つ",
      "招待状が届く"
    ],
    "readings": {
      "バスを待つ": "バスをマつ",
      "招待状が届く": "招タイ状が届く"
    }
  },
  {
    "kanji": "代",
    "yomi": "ダイ、タイ、かえる、かわる、よ、しろ",
    "meaning": "かわる",
    "examples": [
      "お代わりをする",
      "江戸時代"
    ],
    "readings": {
      "お代わりをする": "おカわりをする",
      "江戸時代": "江戸時ダイ"
    }
  },
  {
    "kanji": "第",
    "yomi": "ダイ",
    "meaning": "つぎ",
    "examples": [
      "第一問を解く",
      "次第に晴れる"
    ],
    "readings": {
      "第一問を解く": "ダイ一問を解く",
      "次第に晴れる": "次ダイに晴れる"
    }
  },
  {
    "kanji": "題",
    "yomi": "ダイ",
    "meaning": "だい",
    "examples": [
      "宿題をやる",
      "話題になる"
    ],
    "readings": {
      "宿題をやる": "宿ダイをやる",
      "話題になる": "話ダイになる"
    }
  },
  {
    "kanji": "炭",
    "yomi": "タン、すみ",
    "meaning": "すみ",
    "examples": [
      "炭火でやく",
      "石炭をほる"
    ],
    "readings": {
      "炭火でやく": "スミ火でやく",
      "石炭をほる": "石タンをほる"
    }
  },
  {
    "kanji": "短",
    "yomi": "タン、みじかい",
    "meaning": "みじかい",
    "examples": [
      "ひもが短い",
      "短気な人はきらい"
    ],
    "readings": {
      "ひもが短い": "ひもがミジカい",
      "短気な人はきらい": "タン気な人はきらい"
    }
  },
  {
    "kanji": "談",
    "yomi": "ダン",
    "meaning": "かたる",
    "examples": [
      "相談する",
      "冗（じょう）談を言う"
    ],
    "readings": {
      "相談する": "相ダンする",
      "冗（じょう）談を言う": "冗（じょう）ダンを言う"
    }
  },
  {
    "kanji": "着",
    "yomi": "チャク、ジャク、きる、きせる、つく、つける",
    "meaning": "きる",
    "examples": [
      "上着を着る",
      "えきに到（とう）着"
    ],
    "readings": {
      "上着を着る": "上着をキる",
      "えきに到（とう）着": "えきに到（とう）チャク"
    }
  },
  {
    "kanji": "注",
    "yomi": "チュウ、そそぐ",
    "meaning": "そそぐ",
    "examples": [
      "車に注意する",
      "料理を注文"
    ],
    "readings": {
      "車に注意する": "車にチュウ意する",
      "料理を注文": "料理をチュウ文"
    }
  },
  {
    "kanji": "柱",
    "yomi": "チュウ、はしら",
    "meaning": "はしら",
    "examples": [
      "家の柱",
      "電柱にのぼる"
    ],
    "readings": {
      "家の柱": "家のハシラ",
      "電柱にのぼる": "電チュウにのぼる"
    }
  },
  {
    "kanji": "丁",
    "yomi": "チョウ、テイ、ひのと",
    "meaning": "ひのと",
    "examples": [
      "三丁目に行く",
      "包（ほう）丁を使う"
    ],
    "readings": {
      "三丁目に行く": "三チョウ目に行く",
      "包（ほう）丁を使う": "包（ほう）チョウを使う"
    }
  },
  {
    "kanji": "帳",
    "yomi": "チョウ、とばり",
    "meaning": "とばり",
    "examples": [
      "手帳に書く",
      "電話帳を見る"
    ],
    "readings": {
      "手帳に書く": "手チョウに書く",
      "電話帳を見る": "電話チョウを見る"
    }
  },
  {
    "kanji": "調",
    "yomi": "チョウ、しらべる、しらべ、ととのえる、ととのう",
    "meaning": "しらべる",
    "examples": [
      "意味を調べる",
      "体の調子が良い"
    ],
    "readings": {
      "意味を調べる": "意味をシラべる",
      "体の調子が良い": "体のチョウ子が良い"
    }
  },
  {
    "kanji": "追",
    "yomi": "ツイ、おう",
    "meaning": "おう",
    "examples": [
      "追いかける",
      "手紙の追伸（しん）"
    ],
    "readings": {
      "追いかける": "オいかける",
      "手紙の追伸（しん）": "手紙のツイ伸（しん）"
    }
  },
  {
    "kanji": "定",
    "yomi": "テイ、ジョウ、さだめる、さだまる、さだか",
    "meaning": "さだめる",
    "examples": [
      "定規で線を引く",
      "遠足の予定"
    ],
    "readings": {
      "定規で線を引く": "ジョウ規で線を引く",
      "遠足の予定": "遠足の予テイ"
    }
  },
  {
    "kanji": "庭",
    "yomi": "テイ、にわ",
    "meaning": "にわ",
    "examples": [
      "庭であそぶ",
      "広い校庭"
    ],
    "readings": {
      "広い校庭": "広い校テイ",
      "庭であそぶ": "ニワであそぶ"
    }
  },
  {
    "kanji": "笛",
    "yomi": "テキ、ふえ",
    "meaning": "ふえ",
    "examples": [
      "笛をふく",
      "汽笛の音"
    ],
    "readings": {
      "笛をふく": "フエをふく",
      "汽笛の音": "汽テキの音"
    }
  },
  {
    "kanji": "鉄",
    "yomi": "テツ、くろがね",
    "meaning": "くろがね",
    "examples": [
      "地下鉄に乗る",
      "鉄棒（ぼう）をする"
    ],
    "readings": {
      "地下鉄に乗る": "地下テツに乗る",
      "鉄棒（ぼう）をする": "テツ棒（ぼう）をする"
    }
  },
  {
    "kanji": "転",
    "yomi": "テン、ころがる、ころげる、ころがす、ころぶ",
    "meaning": "ころがる",
    "examples": [
      "道で転ぶ",
      "自転車に乗る"
    ],
    "readings": {
      "道で転ぶ": "道でコロぶ",
      "自転車に乗る": "自テン車に乗る"
    }
  },
  {
    "kanji": "都",
    "yomi": "ト、ツ、みやこ",
    "meaning": "みやこ",
    "examples": [
      "都会にすむ",
      "東京都に行く"
    ],
    "readings": {
      "東京都に行く": "東京トに行く",
      "都会にすむ": "ト会にすむ"
    }
  },
  {
    "kanji": "度",
    "yomi": "ド、ト、タク、たび",
    "meaning": "たび",
    "examples": [
      "一度だけ言う",
      "今度あそぼう"
    ],
    "readings": {
      "一度だけ言う": "一ドだけ言う",
      "今度あそぼう": "今ドあそぼう"
    }
  },
  {
    "kanji": "投",
    "yomi": "トウ、なげる",
    "meaning": "なげる",
    "examples": [
      "ボールを投げる",
      "投球（きゅう）れんしゅう"
    ],
    "readings": {
      "ボールを投げる": "ボールをナげる",
      "投球（きゅう）れんしゅう": "トウ球（きゅう）れんしゅう"
    }
  },
  {
    "kanji": "豆",
    "yomi": "トウ、ズ、まめ",
    "meaning": "まめ",
    "examples": [
      "豆まきをする",
      "大豆をつくる"
    ],
    "readings": {
      "豆まきをする": "マメまきをする",
      "大豆をつくる": "大ズをつくる"
    }
  },
  {
    "kanji": "島",
    "yomi": "トウ、しま",
    "meaning": "しま",
    "examples": [
      "島国日本",
      "無人（むじん）島に行く"
    ],
    "readings": {
      "島国日本": "シマ国日本",
      "無人（むじん）島に行く": "無人（むじん）トウに行く"
    }
  },
  {
    "kanji": "湯",
    "yomi": "トウ、ゆ",
    "meaning": "ゆ",
    "examples": [
      "お湯をわかす",
      "熱湯を入れる"
    ],
    "readings": {
      "お湯をわかす": "おユをわかす",
      "熱湯を入れる": "熱トウを入れる"
    }
  },
  {
    "kanji": "登",
    "yomi": "トウ、ト、のぼる",
    "meaning": "のぼる",
    "examples": [
      "山に登る",
      "ステージに登場"
    ],
    "readings": {
      "山に登る": "山にノボる",
      "ステージに登場": "ステージにトウ場"
    }
  },
  {
    "kanji": "等",
    "yomi": "トウ、ひとしい",
    "meaning": "ひとしい",
    "examples": [
      "一等賞（しょう）をとる",
      "平等に分ける"
    ],
    "readings": {
      "平等に分ける": "平トウに分ける",
      "一等賞（しょう）をとる": "一トウ賞（しょう）をとる"
    }
  },
  {
    "kanji": "動",
    "yomi": "ドウ、うごく、うごかす",
    "meaning": "うごく",
    "examples": [
      "車が動く",
      "動物園に行く"
    ],
    "readings": {
      "車が動く": "車がウゴく",
      "動物園に行く": "ドウ物園に行く"
    }
  },
  {
    "kanji": "童",
    "yomi": "ドウ、わらべ",
    "meaning": "わらべ",
    "examples": [
      "童話を読む",
      "児童館で遊ぶ"
    ],
    "readings": {
      "童話を読む": "ドウ話を読む",
      "児童館で遊ぶ": "児ドウ館で遊ぶ"
    }
  },
  {
    "kanji": "農",
    "yomi": "ノウ",
    "meaning": "たがやす",
    "examples": [
      "農家の仕事",
      "農業を営む"
    ],
    "readings": {
      "農家の仕事": "ノウ家の仕事",
      "農業を営む": "ノウ業を営む"
    }
  },
  {
    "kanji": "波",
    "yomi": "ハ、なみ",
    "meaning": "なみ",
    "examples": [
      "波に乗る",
      "電波がとどく"
    ],
    "readings": {
      "波に乗る": "ナミに乗る",
      "電波がとどく": "電パがとどく"
    }
  },
  {
    "kanji": "配",
    "yomi": "ハイ、くばる",
    "meaning": "くばる",
    "examples": [
      "新聞を配る",
      "心配する"
    ],
    "readings": {
      "新聞を配る": "新聞をクバる",
      "心配する": "心パイする"
    }
  },
  {
    "kanji": "倍",
    "yomi": "バイ",
    "meaning": "ます",
    "examples": [
      "二倍にする",
      "倍にふえる"
    ],
    "readings": {
      "二倍にする": "二バイにする",
      "倍にふえる": "バイにふえる"
    }
  },
  {
    "kanji": "箱",
    "yomi": "ソウ、はこ",
    "meaning": "はこ",
    "examples": [
      "箱に入れる",
      "ゴミ箱に捨てる"
    ],
    "readings": {
      "箱に入れる": "ハコに入れる",
      "ゴミ箱に捨てる": "ゴミバコに捨てる"
    }
  },
  {
    "kanji": "畑",
    "yomi": "はた、はたけ",
    "meaning": "はたけ",
    "examples": [
      "畑仕事をする",
      "茶畑に行く"
    ],
    "readings": {
      "畑仕事をする": "ハタケ仕事をする",
      "茶畑に行く": "茶バタケに行く"
    }
  },
  {
    "kanji": "発",
    "yomi": "ハツ、ホツ、たつ",
    "meaning": "たつ",
    "examples": [
      "作文の発表",
      "旅（たび）に出発する"
    ],
    "readings": {
      "作文の発表": "作文のハッ表",
      "旅（たび）に出発する": "旅（たび）に出パツする"
    }
  },
  {
    "kanji": "反",
    "yomi": "ハン、ホン、タン、そる、そらす",
    "meaning": "そる",
    "examples": [
      "反対の意見",
      "反省（せい）する"
    ],
    "readings": {
      "反対の意見": "ハン対の意見",
      "反省（せい）する": "ハン省（せい）する"
    }
  },
  {
    "kanji": "坂",
    "yomi": "ハン、さか",
    "meaning": "さか",
    "examples": [
      "坂道を歩く",
      "急な上り坂"
    ],
    "readings": {
      "坂道を歩く": "サカ道を歩く",
      "急な上り坂": "急な上りザカ"
    }
  },
  {
    "kanji": "板",
    "yomi": "ハン、バン、いた",
    "meaning": "いた",
    "examples": [
      "板を作る",
      "黒板に書く"
    ],
    "readings": {
      "黒板に書く": "黒バンに書く",
      "板を作る": "イタを作る"
    }
  },
  {
    "kanji": "皮",
    "yomi": "ヒ、かわ",
    "meaning": "かわ",
    "examples": [
      "リンゴの皮",
      "毛皮のコート"
    ],
    "readings": {
      "リンゴの皮": "リンゴのカワ",
      "毛皮のコート": "毛ガワのコート"
    }
  },
  {
    "kanji": "悲",
    "yomi": "ヒ、かなしい、かなしむ",
    "meaning": "かなしい",
    "examples": [
      "悲しい話",
      "悲劇（げき）を見る"
    ],
    "readings": {
      "悲しい話": "カナしい話",
      "悲劇（げき）を見る": "ヒ劇（げき）を見る"
    }
  },
  {
    "kanji": "美",
    "yomi": "ビ、うつくしい",
    "meaning": "うつくしい",
    "examples": [
      "美しい花",
      "美人が多い"
    ],
    "readings": {
      "美しい花": "ウツクしい花",
      "美人が多い": "ビ人が多い"
    }
  },
  {
    "kanji": "鼻",
    "yomi": "ビ、はな",
    "meaning": "はな",
    "examples": [
      "鼻が高い",
      "耳（じ）鼻科に行く"
    ],
    "readings": {
      "鼻が高い": "ハナが高い",
      "耳（じ）鼻科に行く": "耳（じ）ビ科に行く"
    }
  },
  {
    "kanji": "筆",
    "yomi": "ヒツ、ふで",
    "meaning": "ふで",
    "examples": [
      "鉛（えん）筆で書く",
      "筆箱に入れる"
    ],
    "readings": {
      "筆箱に入れる": "フデ箱に入れる",
      "鉛（えん）筆で書く": "鉛（えん）ピツで書く"
    }
  },
  {
    "kanji": "氷",
    "yomi": "ヒョウ、こおり、ひ",
    "meaning": "こおり",
    "examples": [
      "氷がとける",
      "大きな氷山"
    ],
    "readings": {
      "氷がとける": "コオリがとける",
      "大きな氷山": "大きなヒョウ山"
    }
  },
  {
    "kanji": "表",
    "yomi": "ヒョウ、おもて、あらわす、あらわれる",
    "meaning": "おもて",
    "examples": [
      "表と裏がある",
      "結果を発表"
    ],
    "readings": {
      "表と裏がある": "オモテと裏がある",
      "結果を発表": "結果をハッ表"
    }
  },
  {
    "kanji": "秒",
    "yomi": "ビョウ",
    "meaning": "とき",
    "examples": [
      "あと一秒",
      "秒読み開始"
    ],
    "readings": {
      "あと一秒": "あと一ビョウ",
      "秒読み開始": "ビョウ読み開始"
    }
  },
  {
    "kanji": "病",
    "yomi": "ビョウ、やむ、やまい",
    "meaning": "やまい",
    "examples": [
      "病院に行く",
      "病気がなおる"
    ],
    "readings": {
      "病院に行く": "ビョウ院に行く",
      "病気がなおる": "ビョウ気がなおる"
    }
  },
  {
    "kanji": "品",
    "yomi": "ヒン、しな",
    "meaning": "しな",
    "examples": [
      "品物を買う",
      "上品な人"
    ],
    "readings": {
      "品物を買う": "シナ物を買う",
      "上品な人": "上ヒンな人"
    }
  },
  {
    "kanji": "負",
    "yomi": "フ、まける、まかす、おう",
    "meaning": "まける",
    "examples": [
      "試合に負ける",
      "勝負をする"
    ],
    "readings": {
      "試合に負ける": "試合にマける",
      "勝負をする": "勝ブをする"
    }
  },
  {
    "kanji": "部",
    "yomi": "ブ、べ",
    "meaning": "わける",
    "examples": [
      "自分の部屋",
      "全部食べる"
    ],
    "readings": {
      "自分の部屋": "自分のヘ屋",
      "全部食べる": "全ブ食べる"
    }
  },
  {
    "kanji": "服",
    "yomi": "フク",
    "meaning": "きもの",
    "examples": [
      "服を着る",
      "洋（よう）服を買う"
    ],
    "readings": {
      "服を着る": "フクを着る",
      "洋（よう）服を買う": "洋（よう）フクを買う"
    }
  },
  {
    "kanji": "福",
    "yomi": "フク",
    "meaning": "さいわい",
    "examples": [
      "幸福をいのる",
      "福引きをする"
    ],
    "readings": {
      "幸福をいのる": "幸フクをいのる",
      "福引きをする": "フク引きをする"
    }
  },
  {
    "kanji": "物",
    "yomi": "ブツ、モツ、もの",
    "meaning": "もの",
    "examples": [
      "買い物をたのむ",
      "動物園に行く"
    ],
    "readings": {
      "動物園に行く": "動ブツ園に行く",
      "買い物をたのむ": "買いモノをたのむ"
    }
  },
  {
    "kanji": "平",
    "yomi": "ヘイ、ビョウ、たいら、ひら",
    "meaning": "たいら",
    "examples": [
      "平和な世界",
      "平らな道"
    ],
    "readings": {
      "平和な世界": "ヘイ和な世界",
      "平らな道": "タイラな道"
    }
  },
  {
    "kanji": "返",
    "yomi": "ヘン、かえす、かえる",
    "meaning": "かえす",
    "examples": [
      "返事をする",
      "本を返す"
    ],
    "readings": {
      "返事をする": "ヘン事をする",
      "本を返す": "本をカエす"
    }
  },
  {
    "kanji": "勉",
    "yomi": "ベン、つとめる",
    "meaning": "つとめる",
    "examples": [
      "勉強をする",
      "勤（きん）勉にはたらく"
    ],
    "readings": {
      "勉強をする": "ベン強をする",
      "勤（きん）勉にはたらく": "勤（きん）ベンにはたらく"
    }
  },
  {
    "kanji": "放",
    "yomi": "ホウ、はなす、はなつ、はなれる",
    "meaning": "はなす",
    "examples": [
      "放送を聞く",
      "手放す"
    ],
    "readings": {
      "放送を聞く": "ホウ送を聞く",
      "手放す": "手バナす"
    }
  },
  {
    "kanji": "味",
    "yomi": "ミ、あじ、あじわう",
    "meaning": "あじ",
    "examples": [
      "スープの味見",
      "意味をしらべる"
    ],
    "readings": {
      "スープの味見": "スープのアジ見",
      "意味をしらべる": "意ミをしらべる"
    }
  },
  {
    "kanji": "命",
    "yomi": "メイ、ミョウ、いのち",
    "meaning": "いのち",
    "examples": [
      "命を大切に",
      "命令を守る"
    ],
    "readings": {
      "命を大切に": "イノチを大切に",
      "命令を守る": "メイ令を守る"
    }
  },
  {
    "kanji": "面",
    "yomi": "メン、おも、おもて、つら",
    "meaning": "おもて",
    "examples": [
      "面白い本",
      "テレビの画面"
    ],
    "readings": {
      "面白い本": "オモ白い本",
      "テレビの画面": "テレビの画メン"
    }
  },
  {
    "kanji": "問",
    "yomi": "モン、とう、とい",
    "meaning": "とう",
    "examples": [
      "先生に質問",
      "問題を解く"
    ],
    "readings": {
      "先生に質問": "先生に質モン",
      "問題を解く": "モン題を解く"
    }
  },
  {
    "kanji": "役",
    "yomi": "ヤク、エキ",
    "meaning": "つとめ",
    "examples": [
      "役に立つ",
      "げきの主役"
    ],
    "readings": {
      "役に立つ": "ヤクに立つ",
      "げきの主役": "げきの主ヤク"
    }
  },
  {
    "kanji": "薬",
    "yomi": "ヤク、くすり",
    "meaning": "くすり",
    "examples": [
      "薬を飲む",
      "薬局に行く"
    ],
    "readings": {
      "薬を飲む": "クスリを飲む",
      "薬局に行く": "ヤッ局に行く"
    }
  },
  {
    "kanji": "由",
    "yomi": "ユ、ユウ、ユイ、よし",
    "meaning": "よし",
    "examples": [
      "自由な時間",
      "休む理由"
    ],
    "readings": {
      "自由な時間": "自ユウな時間",
      "休む理由": "休む理ユウ"
    }
  },
  {
    "kanji": "油",
    "yomi": "ユ、あぶら",
    "meaning": "あぶら",
    "examples": [
      "油絵をかく",
      "石油ストーブ"
    ],
    "readings": {
      "石油ストーブ": "石ユストーブ",
      "油絵をかく": "アブラ絵をかく"
    }
  },
  {
    "kanji": "有",
    "yomi": "ユウ、ウ、ある",
    "meaning": "ある",
    "examples": [
      "有名な選手（せんしゅ）",
      "有るか無いか"
    ],
    "readings": {
      "有るか無いか": "アるか無いか",
      "有名な選手（せんしゅ）": "ユウ名な選手（せんしゅ）"
    }
  },
  {
    "kanji": "遊",
    "yomi": "ユウ、ユ、あそぶ",
    "meaning": "あそぶ",
    "examples": [
      "公園で遊ぶ",
      "遊園地に行く"
    ],
    "readings": {
      "公園で遊ぶ": "公園でアソぶ",
      "遊園地に行く": "ユウ園地に行く"
    }
  },
  {
    "kanji": "予",
    "yomi": "ヨ、あらかじめ",
    "meaning": "あらかじめ",
    "examples": [
      "明日の予定",
      "天気予報（ほう）"
    ],
    "readings": {
      "明日の予定": "明日のヨ定",
      "天気予報（ほう）": "天気ヨ報（ほう）"
    }
  },
  {
    "kanji": "羊",
    "yomi": "ヨウ、ひつじ",
    "meaning": "ひつじ",
    "examples": [
      "羊が草を食べる",
      "羊毛のセーター"
    ],
    "readings": {
      "羊が草を食べる": "ヒツジが草を食べる",
      "羊毛のセーター": "ヨウ毛のセーター"
    }
  },
  {
    "kanji": "洋",
    "yomi": "ヨウ",
    "meaning": "なだ",
    "examples": [
      "洋服を着る",
      "西洋の文化"
    ],
    "readings": {
      "洋服を着る": "ヨウ服を着る",
      "西洋の文化": "西ヨウの文化"
    }
  },
  {
    "kanji": "葉",
    "yomi": "ヨウ、は",
    "meaning": "は",
    "examples": [
      "落ち葉ひろい",
      "やさしい言葉"
    ],
    "readings": {
      "落ち葉ひろい": "落ちバひろい",
      "やさしい言葉": "やさしい言バ"
    }
  },
  {
    "kanji": "陽",
    "yomi": "ヨウ、ひ",
    "meaning": "ひ",
    "examples": [
      "太陽が出る",
      "陽気な人"
    ],
    "readings": {
      "太陽が出る": "太ヨウが出る",
      "陽気な人": "ヨウ気な人"
    }
  },
  {
    "kanji": "様",
    "yomi": "ヨウ、さま",
    "meaning": "さま",
    "examples": [
      "神様にお願い",
      "様子を見る"
    ],
    "readings": {
      "神様にお願い": "神サマにお願い",
      "様子を見る": "ヨウ子を見る"
    }
  },
  {
    "kanji": "落",
    "yomi": "ラク、おちる、おとす",
    "meaning": "おちる",
    "examples": [
      "木から落ちる",
      "落語を聞く"
    ],
    "readings": {
      "木から落ちる": "木からオちる",
      "落語を聞く": "ラク語を聞く"
    }
  },
  {
    "kanji": "流",
    "yomi": "リュウ、ル、ながれる、ながす",
    "meaning": "ながれる",
    "examples": [
      "川が流れる",
      "流行の歌"
    ],
    "readings": {
      "川が流れる": "川がナガれる",
      "流行の歌": "リュウ行の歌"
    }
  },
  {
    "kanji": "旅",
    "yomi": "リョ、たび",
    "meaning": "たび",
    "examples": [
      "家族旅行",
      "旅に出る"
    ],
    "readings": {
      "家族旅行": "家族リョ行",
      "旅に出る": "タビに出る"
    }
  },
  {
    "kanji": "両",
    "yomi": "リョウ",
    "meaning": "ふたつ",
    "examples": [
      "両手を使う",
      "両親に話す"
    ],
    "readings": {
      "両手を使う": "リョウ手を使う",
      "両親に話す": "リョウ親に話す"
    }
  },
  {
    "kanji": "緑",
    "yomi": "リョク、みどり",
    "meaning": "みどり",
    "examples": [
      "緑色の葉",
      "新緑の季節（きせつ）"
    ],
    "readings": {
      "緑色の葉": "ミドリ色の葉",
      "新緑の季節（きせつ）": "新リョクの季節（きせつ）"
    }
  },
  {
    "kanji": "礼",
    "yomi": "レイ、ライ",
    "meaning": "いや",
    "examples": [
      "お礼を言う",
      "失礼します"
    ],
    "readings": {
      "お礼を言う": "おレイを言う",
      "失礼します": "失レイします"
    }
  },
  {
    "kanji": "列",
    "yomi": "レツ",
    "meaning": "つらなる",
    "examples": [
      "行列に並ぶ",
      "列車に乗る"
    ],
    "readings": {
      "行列に並ぶ": "行レツに並ぶ",
      "列車に乗る": "レッ車に乗る"
    }
  },
  {
    "kanji": "練",
    "yomi": "レン、ねる",
    "meaning": "ねる",
    "examples": [
      "サッカーの練習",
      "案を練る"
    ],
    "readings": {
      "サッカーの練習": "サッカーのレン習",
      "案を練る": "案をネる"
    }
  },
  {
    "kanji": "路",
    "yomi": "ロ、みち",
    "meaning": "みち",
    "examples": [
      "道路をわたる",
      "家路につく"
    ],
    "readings": {
      "家路につく": "家ジにつく",
      "道路をわたる": "道ロをわたる"
    }
  },
  {
    "kanji": "和",
    "yomi": "ワ、オ、やわらぐ、やわらげる、なごむ、なごやか",
    "meaning": "やわらぐ",
    "examples": [
      "平和な国",
      "和食を食べる"
    ],
    "readings": {
      "平和な国": "平ワな国",
      "和食を食べる": "ワ食を食べる"
    }
  }
]